hisensetv/__init__.py
hisensetv/__main__.py
hisensetv-0.3.0.dist-info/entry_points.txt
hisensetv-0.3.0.dist-info/WHEEL
hisensetv-0.3.0.dist-info/METADATA
hisensetv-0.3.0.dist-info/RECORD
