Metadata-Version: 2.1
Name: hisensetv
Version: 0.3.0
Summary: MQTT interface to Hisense televisions.
Home-page: https://github.com/newAM/hisensetv
License: MIT
Author: Alex Martens
Author-email: alex@thinglab.org
Requires-Python: >=3.7,<4.0
Classifier: License :: OSI Approved :: MIT License
Classifier: Programming Language :: Python :: 3
Classifier: Programming Language :: Python :: 3.10
Classifier: Programming Language :: Python :: 3.7
Classifier: Programming Language :: Python :: 3.8
Classifier: Programming Language :: Python :: 3.9
Requires-Dist: paho-mqtt (>=1.5,<2.0)
Project-URL: Repository, https://github.com/newAM/hisensetv
